secretsharing/__init__.py
secretsharing/polynomials.py
secretsharing/primes.py
secretsharing/sharing.py
secret_sharing-0.2.6.dist-info/AUTHORS
secret_sharing-0.2.6.dist-info/LICENSE
secret_sharing-0.2.6.dist-info/METADATA
secret_sharing-0.2.6.dist-info/WHEEL
secret_sharing-0.2.6.dist-info/top_level.txt
secret_sharing-0.2.6.dist-info/RECORD
