Metadata-Version: 2.1
Name: secret-sharing
Version: 0.2.6
Summary: Tools for sharing secrets (like Bitcoin private keys), using shamir's secret sharing scheme.
Home-page: https://github.com/springlabs/secret-sharing
Author: Halfmoon Labs
Author-email: hello@halfmoon.io
License: MIT
Platform: UNKNOWN
Classifier: Intended Audience :: Developers
Classifier: License :: OSI Approved :: MIT License
Classifier: Operating System :: OS Independent
Classifier: Programming Language :: Python :: 2.7
Classifier: Programming Language :: Python :: 3.4
Requires-Dist: six
Requires-Dist: utilitybelt
